{"af":{"one":"%1$s == 1"},"ak":{"one":"static::inRange(%1$s, true, array(0, 1))"},"am":{"one":"%2$s == 0 or %1$s == 1"},"ar":{"zero":"%1$s == 0","one":"%1$s == 1","two":"%1$s == 2","few":"static::inRange(%1$s %% 100, true, array(3, 10))","many":"static::inRange(%1$s %% 100, true, array(11, 99))"},"as":{"one":"%2$s == 0 or %1$s == 1"},"asa":{"one":"%1$s == 1"},"ast":{"one":"%2$s == 1 and %3$s == 0"},"az":{"one":"%1$s == 1"},"be":{"one":"%1$s %% 10 == 1 and %1$s %% 100 != 11","few":"static::inRange(%1$s %% 10, true, array(2, 4)) and static::inRange(%1$s %% 100, false, array(12, 14))","many":"%1$s %% 10 == 0 or static::inRange(%1$s %% 10, true, array(5, 9)) or static::inRange(%1$s %% 100, true, array(11, 14))"},"bem":{"one":"%1$s == 1"},"bez":{"one":"%1$s == 1"},"bg":{"one":"%1$s == 1"},"bh":{"one":"static::inRange(%1$s, true, array(0, 1))"},"bm":[],"bn":{"one":"%2$s == 0 or %1$s == 1"},"bo":[],"br":{"one":"%1$s %% 10 == 1 and static::inRange(%1$s %% 100, false, 11, 71, 91)","two":"%1$s %% 10 == 2 and static::inRange(%1$s %% 100, false, 12, 72, 92)","few":"static::inRange(%1$s %% 10, true, array(3, 4), 9) and static::inRange(%1$s %% 100, false, array(10, 19), array(70, 79), array(90, 99))","many":"%1$s != 0 and %1$s %% 1000000 == 0"},"brx":{"one":"%1$s == 1"},"bs":{"one":"%3$s == 0 and %2$s %% 10 == 1 and %2$s %% 100 != 11 or %5$s %% 10 == 1 and %5$s %% 100 != 11","few":"%3$s == 0 and static::inRange(%2$s %% 10, true, array(2, 4)) and static::inRange(%2$s %% 100, false, array(12, 14)) or static::inRange(%5$s %% 10, true, array(2, 4)) and static::inRange(%5$s %% 100, false, array(12, 14))"},"ca":{"one":"%2$s == 1 and %3$s == 0"},"ce":{"one":"%1$s == 1"},"cgg":{"one":"%1$s == 1"},"chr":{"one":"%1$s == 1"},"ckb":{"one":"%1$s == 1"},"cs":{"one":"%2$s == 1 and %3$s == 0","few":"static::inRange(%2$s, true, array(2, 4)) and %3$s == 0","many":"%3$s != 0"},"cy":{"zero":"%1$s == 0","one":"%1$s == 1","two":"%1$s == 2","few":"%1$s == 3","many":"%1$s == 6"},"da":{"one":"%1$s == 1 or %6$s != 0 and static::inRange(%2$s, true, 0, 1)"},"de":{"one":"%2$s == 1 and %3$s == 0"},"dsb":{"one":"%3$s == 0 and %2$s %% 100 == 1 or %5$s %% 100 == 1","two":"%3$s == 0 and %2$s %% 100 == 2 or %5$s %% 100 == 2","few":"%3$s == 0 and static::inRange(%2$s %% 100, true, array(3, 4)) or static::inRange(%5$s %% 100, true, array(3, 4))"},"dv":{"one":"%1$s == 1"},"dz":[],"ee":{"one":"%1$s == 1"},"el":{"one":"%1$s == 1"},"en":{"one":"%2$s == 1 and %3$s == 0"},"eo":{"one":"%1$s == 1"},"es":{"one":"%1$s == 1"},"et":{"one":"%2$s == 1 and %3$s == 0"},"eu":{"one":"%1$s == 1"},"fa":{"one":"%2$s == 0 or %1$s == 1"},"ff":{"one":"static::inRange(%2$s, true, 0, 1)"},"fi":{"one":"%2$s == 1 and %3$s == 0"},"fil":{"one":"%3$s == 0 and static::inRange(%2$s, true, 1, 2, 3) or %3$s == 0 and static::inRange(%2$s %% 10, false, 4, 6, 9) or %3$s != 0 and static::inRange(%5$s %% 10, false, 4, 6, 9)"},"fo":{"one":"%1$s == 1"},"fr":{"one":"static::inRange(%2$s, true, 0, 1)"},"fur":{"one":"%1$s == 1"},"fy":{"one":"%2$s == 1 and %3$s == 0"},"ga":{"one":"%1$s == 1","two":"%1$s == 2","few":"static::inRange(%1$s, true, array(3, 6))","many":"static::inRange(%1$s, true, array(7, 10))"},"gd":{"one":"static::inRange(%1$s, true, 1, 11)","two":"static::inRange(%1$s, true, 2, 12)","few":"static::inRange(%1$s, true, array(3, 10), array(13, 19))"},"gl":{"one":"%2$s == 1 and %3$s == 0"},"gsw":{"one":"%1$s == 1"},"gu":{"one":"%2$s == 0 or %1$s == 1"},"guw":{"one":"static::inRange(%1$s, true, array(0, 1))"},"gv":{"one":"%3$s == 0 and %2$s %% 10 == 1","two":"%3$s == 0 and %2$s %% 10 == 2","few":"%3$s == 0 and static::inRange(%2$s %% 100, true, 0, 20, 40, 60, 80)","many":"%3$s != 0"},"ha":{"one":"%1$s == 1"},"haw":{"one":"%1$s == 1"},"he":{"one":"%2$s == 1 and %3$s == 0","two":"%2$s == 2 and %3$s == 0","many":"%3$s == 0 and static::inRange(%1$s, false, array(0, 10)) and %1$s %% 10 == 0"},"hi":{"one":"%2$s == 0 or %1$s == 1"},"hr":{"one":"%3$s == 0 and %2$s %% 10 == 1 and %2$s %% 100 != 11 or %5$s %% 10 == 1 and %5$s %% 100 != 11","few":"%3$s == 0 and static::inRange(%2$s %% 10, true, array(2, 4)) and static::inRange(%2$s %% 100, false, array(12, 14)) or static::inRange(%5$s %% 10, true, array(2, 4)) and static::inRange(%5$s %% 100, false, array(12, 14))"},"hsb":{"one":"%3$s == 0 and %2$s %% 100 == 1 or %5$s %% 100 == 1","two":"%3$s == 0 and %2$s %% 100 == 2 or %5$s %% 100 == 2","few":"%3$s == 0 and static::inRange(%2$s %% 100, true, array(3, 4)) or static::inRange(%5$s %% 100, true, array(3, 4))"},"hu":{"one":"%1$s == 1"},"hy":{"one":"static::inRange(%2$s, true, 0, 1)"},"id":[],"ig":[],"ii":[],"in":[],"is":{"one":"%6$s == 0 and %2$s %% 10 == 1 and %2$s %% 100 != 11 or %6$s != 0"},"it":{"one":"%2$s == 1 and %3$s == 0"},"iu":{"one":"%1$s == 1","two":"%1$s == 2"},"iw":{"one":"%2$s == 1 and %3$s == 0","two":"%2$s == 2 and %3$s == 0","many":"%3$s == 0 and static::inRange(%1$s, false, array(0, 10)) and %1$s %% 10 == 0"},"ja":[],"jbo":[],"jgo":{"one":"%1$s == 1"},"ji":{"one":"%2$s == 1 and %3$s == 0"},"jmc":{"one":"%1$s == 1"},"jv":[],"jw":[],"ka":{"one":"%1$s == 1"},"kab":{"one":"static::inRange(%2$s, true, 0, 1)"},"kaj":{"one":"%1$s == 1"},"kcg":{"one":"%1$s == 1"},"kde":[],"kea":[],"kk":{"one":"%1$s == 1"},"kkj":{"one":"%1$s == 1"},"kl":{"one":"%1$s == 1"},"km":[],"kn":{"one":"%2$s == 0 or %1$s == 1"},"ko":[],"ks":{"one":"%1$s == 1"},"ksb":{"one":"%1$s == 1"},"ksh":{"zero":"%1$s == 0","one":"%1$s == 1"},"ku":{"one":"%1$s == 1"},"kw":{"one":"%1$s == 1","two":"%1$s == 2"},"ky":{"one":"%1$s == 1"},"lag":{"zero":"%1$s == 0","one":"static::inRange(%2$s, true, 0, 1) and %1$s != 0"},"lb":{"one":"%1$s == 1"},"lg":{"one":"%1$s == 1"},"lkt":[],"ln":{"one":"static::inRange(%1$s, true, array(0, 1))"},"lo":[],"lt":{"one":"%1$s %% 10 == 1 and static::inRange(%1$s %% 100, false, array(11, 19))","few":"static::inRange(%1$s %% 10, true, array(2, 9)) and static::inRange(%1$s %% 100, false, array(11, 19))","many":"%5$s != 0"},"lv":{"zero":"%1$s %% 10 == 0 or static::inRange(%1$s %% 100, true, array(11, 19)) or %3$s == 2 and static::inRange(%5$s %% 100, true, array(11, 19))","one":"%1$s %% 10 == 1 and %1$s %% 100 != 11 or %3$s == 2 and %5$s %% 10 == 1 and %5$s %% 100 != 11 or %3$s != 2 and %5$s %% 10 == 1"},"mas":{"one":"%1$s == 1"},"mg":{"one":"static::inRange(%1$s, true, array(0, 1))"},"mgo":{"one":"%1$s == 1"},"mk":{"one":"%3$s == 0 and %2$s %% 10 == 1 or %5$s %% 10 == 1"},"ml":{"one":"%1$s == 1"},"mn":{"one":"%1$s == 1"},"mo":{"one":"%2$s == 1 and %3$s == 0","few":"%3$s != 0 or %1$s == 0 or %1$s != 1 and static::inRange(%1$s %% 100, true, array(1, 19))"},"mr":{"one":"%2$s == 0 or %1$s == 1"},"ms":[],"mt":{"one":"%1$s == 1","few":"%1$s == 0 or static::inRange(%1$s %% 100, true, array(2, 10))","many":"static::inRange(%1$s %% 100, true, array(11, 19))"},"my":[],"nah":{"one":"%1$s == 1"},"naq":{"one":"%1$s == 1","two":"%1$s == 2"},"nb":{"one":"%1$s == 1"},"nd":{"one":"%1$s == 1"},"ne":{"one":"%1$s == 1"},"nl":{"one":"%2$s == 1 and %3$s == 0"},"nn":{"one":"%1$s == 1"},"nnh":{"one":"%1$s == 1"},"no":{"one":"%1$s == 1"},"nqo":[],"nr":{"one":"%1$s == 1"},"nso":{"one":"static::inRange(%1$s, true, array(0, 1))"},"ny":{"one":"%1$s == 1"},"nyn":{"one":"%1$s == 1"},"om":{"one":"%1$s == 1"},"or":{"one":"%1$s == 1"},"os":{"one":"%1$s == 1"},"pa":{"one":"static::inRange(%1$s, true, array(0, 1))"},"pap":{"one":"%1$s == 1"},"pl":{"one":"%2$s == 1 and %3$s == 0","few":"%3$s == 0 and static::inRange(%2$s %% 10, true, array(2, 4)) and static::inRange(%2$s %% 100, false, array(12, 14))","many":"%3$s == 0 and %2$s != 1 and static::inRange(%2$s %% 10, true, array(0, 1)) or %3$s == 0 and static::inRange(%2$s %% 10, true, array(5, 9)) or %3$s == 0 and static::inRange(%2$s %% 100, true, array(12, 14))"},"prg":{"zero":"%1$s %% 10 == 0 or static::inRange(%1$s %% 100, true, array(11, 19)) or %3$s == 2 and static::inRange(%5$s %% 100, true, array(11, 19))","one":"%1$s %% 10 == 1 and %1$s %% 100 != 11 or %3$s == 2 and %5$s %% 10 == 1 and %5$s %% 100 != 11 or %3$s != 2 and %5$s %% 10 == 1"},"ps":{"one":"%1$s == 1"},"pt":{"one":"static::inRange(%1$s, true, array(0, 2)) and %1$s != 2"},"pt-PT":{"one":"%1$s == 1 and %3$s == 0"},"rm":{"one":"%1$s == 1"},"ro":{"one":"%2$s == 1 and %3$s == 0","few":"%3$s != 0 or %1$s == 0 or %1$s != 1 and static::inRange(%1$s %% 100, true, array(1, 19))"},"rof":{"one":"%1$s == 1"},"root":[],"ru":{"one":"%3$s == 0 and %2$s %% 10 == 1 and %2$s %% 100 != 11","few":"%3$s == 0 and static::inRange(%2$s %% 10, true, array(2, 4)) and static::inRange(%2$s %% 100, false, array(12, 14))","many":"%3$s == 0 and %2$s %% 10 == 0 or %3$s == 0 and static::inRange(%2$s %% 10, true, array(5, 9)) or %3$s == 0 and static::inRange(%2$s %% 100, true, array(11, 14))"},"rwk":{"one":"%1$s == 1"},"sah":[],"saq":{"one":"%1$s == 1"},"se":{"one":"%1$s == 1","two":"%1$s == 2"},"seh":{"one":"%1$s == 1"},"ses":[],"sg":[],"sh":{"one":"%3$s == 0 and %2$s %% 10 == 1 and %2$s %% 100 != 11 or %5$s %% 10 == 1 and %5$s %% 100 != 11","few":"%3$s == 0 and static::inRange(%2$s %% 10, true, array(2, 4)) and static::inRange(%2$s %% 100, false, array(12, 14)) or static::inRange(%5$s %% 10, true, array(2, 4)) and static::inRange(%5$s %% 100, false, array(12, 14))"},"shi":{"one":"%2$s == 0 or %1$s == 1","few":"static::inRange(%1$s, true, array(2, 10))"},"si":{"one":"static::inRange(%1$s, true, 0, 1) or %2$s == 0 and %5$s == 1"},"sk":{"one":"%2$s == 1 and %3$s == 0","few":"static::inRange(%2$s, true, array(2, 4)) and %3$s == 0","many":"%3$s != 0"},"sl":{"one":"%3$s == 0 and %2$s %% 100 == 1","two":"%3$s == 0 and %2$s %% 100 == 2","few":"%3$s == 0 and static::inRange(%2$s %% 100, true, array(3, 4)) or %3$s != 0"},"sma":{"one":"%1$s == 1","two":"%1$s == 2"},"smi":{"one":"%1$s == 1","two":"%1$s == 2"},"smj":{"one":"%1$s == 1","two":"%1$s == 2"},"smn":{"one":"%1$s == 1","two":"%1$s == 2"},"sms":{"one":"%1$s == 1","two":"%1$s == 2"},"sn":{"one":"%1$s == 1"},"so":{"one":"%1$s == 1"},"sq":{"one":"%1$s == 1"},"sr":{"one":"%3$s == 0 and %2$s %% 10 == 1 and %2$s %% 100 != 11 or %5$s %% 10 == 1 and %5$s %% 100 != 11","few":"%3$s == 0 and static::inRange(%2$s %% 10, true, array(2, 4)) and static::inRange(%2$s %% 100, false, array(12, 14)) or static::inRange(%5$s %% 10, true, array(2, 4)) and static::inRange(%5$s %% 100, false, array(12, 14))"},"ss":{"one":"%1$s == 1"},"ssy":{"one":"%1$s == 1"},"st":{"one":"%1$s == 1"},"sv":{"one":"%2$s == 1 and %3$s == 0"},"sw":{"one":"%2$s == 1 and %3$s == 0"},"syr":{"one":"%1$s == 1"},"ta":{"one":"%1$s == 1"},"te":{"one":"%1$s == 1"},"teo":{"one":"%1$s == 1"},"th":[],"ti":{"one":"static::inRange(%1$s, true, array(0, 1))"},"tig":{"one":"%1$s == 1"},"tk":{"one":"%1$s == 1"},"tl":{"one":"%3$s == 0 and static::inRange(%2$s, true, 1, 2, 3) or %3$s == 0 and static::inRange(%2$s %% 10, false, 4, 6, 9) or %3$s != 0 and static::inRange(%5$s %% 10, false, 4, 6, 9)"},"tn":{"one":"%1$s == 1"},"to":[],"tr":{"one":"%1$s == 1"},"ts":{"one":"%1$s == 1"},"tzm":{"one":"static::inRange(%1$s, true, array(0, 1)) or static::inRange(%1$s, true, array(11, 99))"},"ug":{"one":"%1$s == 1"},"uk":{"one":"%3$s == 0 and %2$s %% 10 == 1 and %2$s %% 100 != 11","few":"%3$s == 0 and static::inRange(%2$s %% 10, true, array(2, 4)) and static::inRange(%2$s %% 100, false, array(12, 14))","many":"%3$s == 0 and %2$s %% 10 == 0 or %3$s == 0 and static::inRange(%2$s %% 10, true, array(5, 9)) or %3$s == 0 and static::inRange(%2$s %% 100, true, array(11, 14))"},"ur":{"one":"%2$s == 1 and %3$s == 0"},"uz":{"one":"%1$s == 1"},"ve":{"one":"%1$s == 1"},"vi":[],"vo":{"one":"%1$s == 1"},"vun":{"one":"%1$s == 1"},"wa":{"one":"static::inRange(%1$s, true, array(0, 1))"},"wae":{"one":"%1$s == 1"},"wo":[],"xh":{"one":"%1$s == 1"},"xog":{"one":"%1$s == 1"},"yi":{"one":"%2$s == 1 and %3$s == 0"},"yo":[],"zh":[],"zu":{"one":"%2$s == 0 or %1$s == 1"}}